anywave/__init__.py
anywave/debug_connect.py
anywave/getdata.py
anywave/getmarkers.py
anywave/getprops.py
anywave/init.py
anywave/requests.py
anywave/run.py
anywave/sendmarkers.py
anywave/sendmessage.py
anywave/test.py
anywave/core/__init__.py
anywave/core/channel.py
anywave/core/marker.py
anywave/network/__init__.py
anywave/network/constants.py
anywave/network/tcprequest.py
anywave_plugin_api-1.0.1.dist-info/licenses/LICENSE
anywave_plugin_api-1.0.1.dist-info/METADATA
anywave_plugin_api-1.0.1.dist-info/WHEEL
anywave_plugin_api-1.0.1.dist-info/top_level.txt
anywave_plugin_api-1.0.1.dist-info/RECORD
